Workbook

Sheet Historical Financials
A1: Historical Financials
A3: Metric ($mm) | B3: FY2022A | C3: FY2023A | D3: FY2024A | E3: FY2025A | F3: FY2026A
A4: Revenue | B4: 46710 | C4: 51217 | D4: 51362 | E4: 46309 | F4: 46398
A5: Cost of Sales | B5: 25231 | C5: 28925 | D5: 28475 | E5: 26519 | F5: 26487
A6: Gross Profit | B6: 21479 | C6: 22292 | D6: 22887 | E6: 19790 | F6: 19911
A7: SG&A | B7: 14804 | C7: 16377 | D7: 16576 | E7: 16088 | F7: 16114
A8: EBIT | B8: 6856 | C8: 6195 | D8: 6539 | E8: 3778 | F8: 3850
A9: Net Income | B9: 6046 | C9: 5070 | D9: 5700 | E9: 3219 | F9: 3108
A10: Diluted EPS | B10: 3.75 | C10: 3.23 | D10: 3.73 | E10: 2.16 | F10: 2.1
A11: Revenue Growth | C11: =C4/B4-1 -> 0.096488975 | D11: =D4/C4-1 -> 0.0028310912 | E11: =E4/D4-1 -> -0.098380125 | F11: =F4/E4-1 -> 0.0019218726
A12: Gross Margin | B12: =B6/B4 -> 0.45983729 | C12: =C6/C4 -> 0.43524611 | D12: =D6/D4 -> 0.44560181 | E12: =E6/E4 -> 0.42734674 | F12: =F6/F4 -> 0.42913488
A13: EBIT Margin | B13: =B8/B4 -> 0.14677799 | C13: =C8/C4 -> 0.12095593 | D13: =D8/D4 -> 0.12731202 | E13: =E8/E4 -> 0.081582414 | F13: =F8/F4 -> 0.082977715
A14: Net Margin | B14: =B9/B4 -> 0.12943695 | C14: =C9/C4 -> 0.09899057 | D14: =D9/D4 -> 0.11097699 | E14: =E9/E4 -> 0.069511326 | F14: =F9/F4 -> 0.066985646
A15: Operating Cash Flow | B15: 5188 | C15: 5841 | D15: 7429 | E15: 3698 | F15: 2868
A16: Capital Expenditure | B16: 758 | C16: 969 | D16: 812 | E16: 430 | F16: 684
A17: Free Cash Flow | B17: =B15-B16 -> 4430 | C17: =C15-C16 -> 4872 | D17: =D15-D16 -> 6617 | E17: =E15-E16 -> 3268 | F17: =F15-F16 -> 2184

Sheet Segment Analysis
A1: Segment Analysis
A3: Metric ($mm) | B3: FY2024A | C3: FY2025A | D3: FY2026A
A4: Nike Brand Revenue | B4: 49322 | C4: 44714 | D4: 45222
A5: Converse Revenue | B5: 2082 | C5: 1692 | D5: 1174
A6: Nike Brand + Converse Revenue | B6: =SUM(B4:B5) -> 51404 | C6: =SUM(C4:C5) -> 46406 | D6: =SUM(D4:D5) -> 46396
A7: Nike Brand Growth | C7: =C4/B4-1 -> -0.093426868 | D7: =D4/C4-1 -> 0.011361095
A8: Converse Growth | C8: =C5/B5-1 -> -0.18731988 | D8: =D5/C5-1 -> -0.30614657

Sheet Assumptions
A1: Assumptions
A3: Revenue Growth Assumptions
A4: Base Case | B4: 0.04
A5: Bull Case | B5: 0.06
A6: Bear Case | B6: 0.01
A8: Margin Assumptions
A9: Base Case | B9: 0.1
A10: Bull Case | B10: 0.11
A11: Bear Case | B11: 0.08
A13: Valuation Assumptions
A14: WACC | B14: 0.09
A15: Terminal Growth Rate | B15: 0.025

Sheet Forecast
A1: Forecast
A3: Metric ($mm) | B3: FY2026A | C3: FY2027E | D3: FY2028E | E3: FY2029E | F3: FY2030E | G3: FY2031E
A4: Revenue | B4: ='Historical Financials'!F4 -> 46398 | C4: =B4*(1+Assumptions!B4) -> 48253.92 | D4: =C4*(1+Assumptions!B4) -> 50184.077 | E4: =D4*(1+Assumptions!B4) -> 52191.44 | F4: =E4*(1+Assumptions!B4) -> 54279.097 | G4: =F4*(1+Assumptions!B4) -> 56450.261
A5: Revenue Growth | B5: ='Historical Financials'!F11 -> 0.0019218726 | C5: =C4/B4-1 -> 0.04 | D5: =D4/C4-1 -> 0.04 | E5: =E4/D4-1 -> 0.04 | F5: =F4/E4-1 -> 0.04 | G5: =G4/F4-1 -> 0.04
A6: Gross Profit | B6: ='Historical Financials'!F6 -> 19911 | C6: =C4*C7 -> 20797.44 | D6: =D4*D7 -> 21729.705 | E6: =E4*E7 -> 22703.276 | F6: =F4*F7 -> 23719.966 | G6: =G4*G7 -> 24838.115
A7: Gross Margin | B7: ='Historical Financials'!F12 -> 0.42913488 | C7: 0.431 | D7: 0.433 | E7: 0.435 | F7: 0.437 | G7: 0.44
A8: Operating Income | B8: ='Historical Financials'!F8 -> 3850 | C8: =C4*C9 -> 4825.392 | D8: =D4*D9 -> 5018.4077 | E8: =E4*E9 -> 5219.144 | F8: =F4*F9 -> 5427.9097 | G8: =G4*G9 -> 5645.0261
A9: Operating Margin | B9: ='Historical Financials'!F13 -> 0.082977715 | C9: =Assumptions!$B9 -> 0.1 | D9: =Assumptions!$B9 -> 0.1 | E9: =Assumptions!$B9 -> 0.1 | F9: =Assumptions!$B9 -> 0.1 | G9: =Assumptions!$B9 -> 0.1
A10: Net Income | B10: =B8*(1-'Cash Flow'!B5) -> 3068.45 | C10: =C8*(1-'Cash Flow'!C5) -> 3845.8374 | D10: =D8*(1-'Cash Flow'!D5) -> 3999.6709 | E10: =E8*(1-'Cash Flow'!E5) -> 4159.6578 | F10: =F8*(1-'Cash Flow'!F5) -> 4326.0441 | G10: =G8*(1-'Cash Flow'!G5) -> 4499.0858
A11: Net Margin | B11: =B10/B4 -> 0.066133239 | C11: =C10/C4 -> 0.0797 | D11: =D10/D4 -> 0.0797 | E11: =E10/E4 -> 0.0797 | F11: =F10/F4 -> 0.0797 | G11: =G10/G4 -> 0.0797

Sheet Cash Flow
A1: Free Cash Flow Forecast
A3: Metric ($mm) | B3: FY2026A | C3: FY2027E | D3: FY2028E | E3: FY2029E | F3: FY2030E | G3: FY2031E
A4: Operating Income | B4: =Forecast!B8 -> 3850 | C4: =Forecast!C8 -> 4825.392 | D4: =Forecast!D8 -> 5018.4077 | E4: =Forecast!E8 -> 5219.144 | F4: =Forecast!F8 -> 5427.9097 | G4: =Forecast!G8 -> 5645.0261
A5: Tax Rate | B5: 0.203 | C5: 0.203 | D5: 0.203 | E5: 0.203 | F5: 0.203 | G5: 0.203
A6: NOPAT | B6: =B4*(1-B5) -> 3068.45 | C6: =C4*(1-C5) -> 3845.8374 | D6: =D4*(1-D5) -> 3999.6709 | E6: =E4*(1-E5) -> 4159.6578 | F6: =F4*(1-F5) -> 4326.0441 | G6: =G4*(1-G5) -> 4499.0858
A7: Depreciation & Amortization | B7: 747 | C7: =C4*1.6% -> 77.206272 | D7: =D4*1.6% -> 80.294523 | E7: =E4*1.6% -> 83.506304 | F7: =F4*1.6% -> 86.846556 | G7: =G4*1.6% -> 90.320418
A8: Capital Expenditure | B8: 684 | C8: =C4*1.5% -> 72.38088 | D8: =D4*1.5% -> 75.276115 | E8: =E4*1.5% -> 78.28716 | F8: =F4*1.5% -> 81.418646 | G8: =G4*1.5% -> 84.675392
A9: Change in Working Capital | B9: 1678 | C9: =C4*1% -> 48.25392 | D9: =D4*1% -> 50.184077 | E9: =E4*1% -> 52.19144 | F9: =F4*1% -> 54.279097 | G9: =G4*1% -> 56.450261
A10: Free Cash Flow | B10: =B6+B7-B8-B9 -> 1453.45 | C10: =C6+C7-C8-C9 -> 3802.4089 | D10: =D6+D7-D8-D9 -> 3954.5053 | E10: =E6+E7-E8-E9 -> 4112.6855 | F10: =F6+F7-F8-F9 -> 4277.1929 | G10: =G6+G7-G8-G9 -> 4448.2806

Sheet DCF
A1: DCF Valuation
A3: Metric ($mm) | B3: FY2027E | C3: FY2028E | D3: FY2029E | E3: FY2030E | F3: FY2031E
A4: Free Cash Flow | B4: ='Cash Flow'!C10 -> 3802.4089 | C4: ='Cash Flow'!D10 -> 3954.5053 | D4: ='Cash Flow'!E10 -> 4112.6855 | E4: ='Cash Flow'!F10 -> 4277.1929 | F4: ='Cash Flow'!G10 -> 4448.2806
A5: Discount Factor | B5: =1/(1+Assumptions!$B14)^1 -> 0.91743119 | C5: =1/(1+Assumptions!$B14)^2 -> 0.84167999 | D5: =1/(1+Assumptions!$B14)^3 -> 0.77218348 | E5: =1/(1+Assumptions!$B14)^4 -> 0.70842521 | F5: =1/(1+Assumptions!$B14)^5 -> 0.64993139
A6: Present Value of FCF | B6: =B4*B5 -> 3488.4485 | C6: =C4*C5 -> 3328.428 | D6: =D4*D5 -> 3175.7478 | E6: =E4*E5 -> 3030.0713 | F6: =F4*F5 -> 2891.0772
A8: Terminal Growth Rate | B8: =Assumptions!B15 -> 0.025
A9: Terminal Value | B9: =F4*(1+B8)/(Assumptions!B14-B8) -> 70145.963
A10: PV of Terminal Value | B10: =B9*F5 -> 45590.063
A12: Enterprise Value | B12: =SUM(B6:F6)+B10 -> 61503.836
A13: Net Debt | B13: =5942-7563-1464 -> -3085
A14: Equity Value | B14: =B12-B13 -> 64588.836
A15: Shares Outstanding (mm) | B15: =1483.5 -> 1483.5
A16: Implied Share Price | B16: =B14/B15 -> 43.538143
A19: DCF Senstivity-Implied Share Price
A20: WACC / Terminal Growth | B20: 0.02 | C20: 0.025 | D20: 0.03
A21: 0.08 | B21: =((SUM($B$4/(1+$A21)^1,$C$4/(1+$A21)^2,$D$4/(1+$A21)^3,$E$4/(1+$A21)^4,$F$4/(1+$A21)^5)+($F$4*(1+B$20)/($A21-B$20))/(1+$A21)^5)-$B$13)/$B$15 -> 47.791302 | C21: =((SUM($B$4/(1+$A21)^1,$C$4/(1+$A21)^2,$D$4/(1+$A21)^3,$E$4/(1+$A21)^4,$F$4/(1+$A21)^5)+($F$4*(1+C$20)/($A21-C$20))/(1+$A21)^5)-$B$13)/$B$15 -> 51.130681 | D21: =((SUM($B$4/(1+$A21)^1,$C$4/(1+$A21)^2,$D$4/(1+$A21)^3,$E$4/(1+$A21)^4,$F$4/(1+$A21)^5)+($F$4*(1+D$20)/($A21-D$20))/(1+$A21)^5)-$B$13)/$B$15 -> 55.137935
A22: 0.09 | B22: =((SUM($B$4/(1+$A22)^1,$C$4/(1+$A22)^2,$D$4/(1+$A22)^3,$E$4/(1+$A22)^4,$F$4/(1+$A22)^5)+($F$4*(1+B$20)/($A22-B$20))/(1+$A22)^5)-$B$13)/$B$15 -> 41.20384 | C22: =((SUM($B$4/(1+$A22)^1,$C$4/(1+$A22)^2,$D$4/(1+$A22)^3,$E$4/(1+$A22)^4,$F$4/(1+$A22)^5)+($F$4*(1+C$20)/($A22-C$20))/(1+$A22)^5)-$B$13)/$B$15 -> 43.538143 | D22: =((SUM($B$4/(1+$A22)^1,$C$4/(1+$A22)^2,$D$4/(1+$A22)^3,$E$4/(1+$A22)^4,$F$4/(1+$A22)^5)+($F$4*(1+D$20)/($A22-D$20))/(1+$A22)^5)-$B$13)/$B$15 -> 46.261497
A23: 0.1 | B23: =((SUM($B$4/(1+$A23)^1,$C$4/(1+$A23)^2,$D$4/(1+$A23)^3,$E$4/(1+$A23)^4,$F$4/(1+$A23)^5)+($F$4*(1+B$20)/($A23-B$20))/(1+$A23)^5)-$B$13)/$B$15 -> 36.265027 | C23: =((SUM($B$4/(1+$A23)^1,$C$4/(1+$A23)^2,$D$4/(1+$A23)^3,$E$4/(1+$A23)^4,$F$4/(1+$A23)^5)+($F$4*(1+C$20)/($A23-C$20))/(1+$A23)^5)-$B$13)/$B$15 -> 37.971709 | D23: =((SUM($B$4/(1+$A23)^1,$C$4/(1+$A23)^2,$D$4/(1+$A23)^3,$E$4/(1+$A23)^4,$F$4/(1+$A23)^5)+($F$4*(1+D$20)/($A23-D$20))/(1+$A23)^5)-$B$13)/$B$15 -> 39.922203

Sheet Trading Comps
A1: Trading Comparables
A3: Company | B3: Ticker | C3: Share Price | D3: Market Cap ($mm) | E3: Enterprise Value ($mm) | F3: Revenue ($mm) | G3: EBITDA ($mm) | H3: P/E | I3: EV/EBITDA
A4: Nike | B4: NKE | C4: 35.51 | D4: 52680 | E4: 54700 | F4: 46400 | G4: 4930 | H4: 17.31 | I4: 11.14
A5: Adidas | B5: ADS | C5: 163.02 | D5: 28364 | E5: 33875 | F5: 29840 | G5: 3049 | H5: 18.27 | I5: 8.95
A6: Puma | B6: PUM | C6: 25.21 | D6: 3713 | E6: 6326 | F6: 8011 | G6: -19 | H6: N/A | I6: 25.7
A7: Lululemon | B7: LULU | C7: 98.06 | D7: 10860 | E7: 11610 | F7: 11090 | G7: 2380 | H7: 8.03 | I7: 4.87
A8: Under Armour | B8: UAA | C8: 4.88 | D8: 2100 | E8: 3080 | F8: 4930 | G8: 173 | H8: N/A | I8: 17.78
A10: Peer Median | H10: =MEDIAN(H4:H8) -> 17.31 | I10: =MEDIAN(I4:I5,I7:I8) -> 10.045
A12: P/E Implied Share Price | B12: =H10*'Historical Financials'!F9/DCF!B15 -> 36.265238
A13: EV/EBITDA Implied Share Price | B13: =(I10*G4-DCF!B13)/DCF!B15 -> 35.461308
A14: Average Implied Share Price | B14: =AVERAGE(B12:B13) -> 35.863273

Sheet Bull Base Bear
A1: Bull/Base/Bear Analysis
A3: Metric | B3: Bear Case | C3: Base Case | D3: Bull Case
A4: Revenue Growth | B4: 0.01 | C4: 0.04 | D4: 0.06
A5: Operating Margin | B5: 0.08 | C5: 0.1 | D5: 0.11
A6: Terminal Growth | B6: 0.02 | C6: 0.025 | D6: 0.03
A7: WACC | B7: 0.1 | C7: 0.09 | D7: 0.08
A9: Implied Share Price
A10: DCF Value
A11: Trading Comps Value
A12: Scenario Value
A14: DCF Implied Share Price | B14: {=(((SUMPRODUCT('Historical Financials'!$F$4*(1+B$4)^{1,2,3,4,5}*B$5*(1-'Cash Flow'!$B$5+1.6%-1.5%-1%)/(1+B$7)^{1,2,3,4,5}))+((('Historical Financials'!$F$4*(1+B$4)^5)*B$5*(1-'Cash Flow'!$B$5+1.6%-1.5%-1%))*(1+B$6)/(B$7-B$6))/(1+B$7)^5)-DCF!$B$13)/DCF!$B$15} -> 26.171504 | C14: {=(((SUMPRODUCT('Historical Financials'!$F$4*(1+C$4)^{1,2,3,4,5}*C$5*(1-'Cash Flow'!$B$5+1.6%-1.5%-1%)/(1+C$7)^{1,2,3,4,5}))+((('Historical Financials'!$F$4*(1+C$4)^5)*C$5*(1-'Cash Flow'!$B$5+1.6%-1.5%-1%))*(1+C$6)/(C$7-C$6))/(1+C$7)^5)-DCF!$B$13)/DCF!$B$15} -> 43.538143 | D14: {=(((SUMPRODUCT('Historical Financials'!$F$4*(1+D$4)^{1,2,3,4,5}*D$5*(1-'Cash Flow'!$B$5+1.6%-1.5%-1%)/(1+D$7)^{1,2,3,4,5}))+((('Historical Financials'!$F$4*(1+D$4)^5)*D$5*(1-'Cash Flow'!$B$5+1.6%-1.5%-1%))*(1+D$6)/(D$7-D$6))/(1+D$7)^5)-DCF!$B$13)/DCF!$B$15} -> 65.763607
A15: Trading Comps Value | B15: ='Trading Comps'!$B$14 -> 35.863273 | C15: ='Trading Comps'!$B$14 -> 35.863273 | D15: ='Trading Comps'!$B$14 -> 35.863273
A16: Scenario Implied Share Price | B16: =AVERAGE(B14,B15) -> 31.017388 | C16: =AVERAGE(C14,C15) -> 39.700708 | D16: =AVERAGE(D14,D15) -> 50.81344

Sheet Valuation Summary
A1: Nike Valuation Summary
A3: Valuation Method | B3: Implied Share Price
A4: DCF | B4: =DCF!B16 -> 43.538143
A5: Trading Comparables | B5: ='Trading Comps'!B14 -> 35.863273
A6: Base Case Scenario | B6: ='Bull Base Bear'!C16 -> 39.700708
A8: Current Share Price | B8: ='Trading Comps'!C4 -> 35.51
A9: Target Share Price | B9: =B6 -> 39.700708
A10: Upside / (Downside) | B10: =B9/B8-1 -> 0.11801487
A11: Recommendation | B11: BUY
A13: Scenario | B13: Implied Share Price
A14: Bear Case | B14: ='Bull Base Bear'!B16 -> 31.017388
A15: Base Case | B15: ='Bull Base Bear'!C16 -> 39.700708
A16: Bull Case | B16: ='Bull Base Bear'!D16 -> 50.81344
